aws_cis_assessment/__init__.py
aws_cis_assessment/cli/__init__.py
aws_cis_assessment/cli/examples.py
aws_cis_assessment/cli/main.py
aws_cis_assessment/cli/utils.py
aws_cis_assessment/config/__init__.py
aws_cis_assessment/config/config_loader.py
aws_cis_assessment/config/rules/cis_controls_ig1.yaml
aws_cis_assessment/config/rules/cis_controls_ig2.yaml
aws_cis_assessment/config/rules/cis_controls_ig3.yaml
aws_cis_assessment/controls/__init__.py
aws_cis_assessment/controls/base_control.py
aws_cis_assessment/controls/ig1/__init__.py
aws_cis_assessment/controls/ig1/control_1_1.py
aws_cis_assessment/controls/ig1/control_2_2.py
aws_cis_assessment/controls/ig1/control_3_3.py
aws_cis_assessment/controls/ig1/control_3_4.py
aws_cis_assessment/controls/ig1/control_4_1.py
aws_cis_assessment/controls/ig1/control_access_keys.py
aws_cis_assessment/controls/ig1/control_advanced_security.py
aws_cis_assessment/controls/ig1/control_aws_backup_service.py
aws_cis_assessment/controls/ig1/control_backup_recovery.py
aws_cis_assessment/controls/ig1/control_cloudtrail_logging.py
aws_cis_assessment/controls/ig1/control_critical_security.py
aws_cis_assessment/controls/ig1/control_data_protection.py
aws_cis_assessment/controls/ig1/control_iam_advanced.py
aws_cis_assessment/controls/ig1/control_iam_governance.py
aws_cis_assessment/controls/ig1/control_iam_policies.py
aws_cis_assessment/controls/ig1/control_instance_optimization.py
aws_cis_assessment/controls/ig1/control_network_enhancements.py
aws_cis_assessment/controls/ig1/control_network_security.py
aws_cis_assessment/controls/ig1/control_s3_enhancements.py
aws_cis_assessment/controls/ig1/control_s3_security.py
aws_cis_assessment/controls/ig1/control_vpc_security.py
aws_cis_assessment/controls/ig2/__init__.py
aws_cis_assessment/controls/ig2/control_3_10.py
aws_cis_assessment/controls/ig2/control_3_11.py
aws_cis_assessment/controls/ig2/control_4_5_6_access_configuration.py
aws_cis_assessment/controls/ig2/control_5_2.py
aws_cis_controls_assessment-1.1.4.dist-info/licenses/LICENSE
aws_cis_controls_assessment-1.1.4.dist-info/METADATA
aws_cis_controls_assessment-1.1.4.dist-info/WHEEL
aws_cis_controls_assessment-1.1.4.dist-info/entry_points.txt
aws_cis_controls_assessment-1.1.4.dist-info/top_level.txt
aws_cis_controls_assessment-1.1.4.dist-info/RECORD
