Metadata-Version: 2.4
Name: aws-cis-controls-assessment
Version: 1.1.4
Summary: Production-ready AWS CIS Controls compliance assessment framework with 145 comprehensive rules
Author-email: AWS CIS Assessment Team <security@example.com>
Maintainer-email: AWS CIS Assessment Team <security@example.com>
License: MIT
Project-URL: Homepage, https://github.com/yourusername/aws-cis-controls-assessment
Project-URL: Documentation, https://github.com/yourusername/aws-cis-controls-assessment/blob/main/README.md
Project-URL: Repository, https://github.com/yourusername/aws-cis-controls-assessment.git
Project-URL: Bug Reports, https://github.com/yourusername/aws-cis-controls-assessment/issues
Project-URL: Changelog, https://github.com/yourusername/aws-cis-controls-assessment/blob/main/CHANGELOG.md
Project-URL: Source Code, https://github.com/yourusername/aws-cis-controls-assessment
Keywords: aws,security,compliance,cis,controls,assessment,audit,enterprise,production
Classifier: Development Status :: 5 - Production/Stable
Classifier: Intended Audience :: System Administrators
Classifier: Intended Audience :: Information Technology
Classifier: Intended Audience :: Developers
Classifier: License :: OSI Approved :: MIT License
Classifier: Operating System :: OS Independent
Classifier: Programming Language :: Python :: 3
Classifier: Programming Language :: Python :: 3.8
Classifier: Programming Language :: Python :: 3.9
Classifier: Programming Language :: Python :: 3.10
Classifier: Programming Language :: Python :: 3.11
Classifier: Programming Language :: Python :: 3.12
Classifier: Topic :: Security
Classifier: Topic :: System :: Systems Administration
Classifier: Topic :: Software Development :: Quality Assurance
Classifier: Environment :: Console
Classifier: Environment :: No Input/Output (Daemon)
Requires-Python: >=3.8
License-File: LICENSE
Requires-Dist: boto3<2.0.0,>=1.26.0
Requires-Dist: PyYAML<7.0,>=6.0
Requires-Dist: click<9.0,>=8.0
Requires-Dist: jinja2<4.0,>=3.0
Requires-Dist: tabulate<1.0,>=0.9.0
Provides-Extra: dev
Requires-Dist: pytest<8.0,>=7.0.0; extra == "dev"
Requires-Dist: pytest-mock<4.0,>=3.10.0; extra == "dev"
Requires-Dist: pytest-cov<5.0,>=4.0.0; extra == "dev"
Requires-Dist: black<24.0,>=22.0.0; extra == "dev"
Requires-Dist: flake8<7.0,>=5.0.0; extra == "dev"
Requires-Dist: mypy<2.0,>=1.0.0; extra == "dev"
Requires-Dist: bandit<2.0,>=1.7.0; extra == "dev"
Requires-Dist: safety<3.0,>=2.0.0; extra == "dev"
Provides-Extra: test
Requires-Dist: pytest<8.0,>=7.0.0; extra == "test"
Requires-Dist: pytest-mock<4.0,>=3.10.0; extra == "test"
Requires-Dist: pytest-cov<5.0,>=4.0.0; extra == "test"
Provides-Extra: security
Requires-Dist: bandit<2.0,>=1.7.0; extra == "security"
Requires-Dist: safety<3.0,>=2.0.0; extra == "security"
Dynamic: license-file
